{"id":"wp-en-15664","wp_id":15664,"type":"standard","category":"World","language":"en","title":"India successfully tests nuclear-capable 3,500 km range ballistic missile ￼","excerpt":"The Indian Navy on Wednesday successfully test-fired the nuclear-capable K-4 ballistic missile with a range of 3,500 km from the recently inducted nuclear submarine INS Arighaat.  According to Defence sources, the test results are being analyzed, after which the officials concerned would be briefing the top military and political leadership. The test is crucial for","author":"Tattva News Team","time":"28/11/2024","image":"https://en.tattvanews.com/wp-content/uploads/2024/11/Missile.webp","readTime":"5 min read","contentHTML":"\n<p>The Indian Navy on Wednesday successfully test-fired the nuclear-capable K-4 ballistic missile with a range of 3,500 km from the recently inducted nuclear submarine INS Arighaat. </p>\n\n\n\n<p>According to Defence sources, the test results are being analyzed, after which the officials concerned would be briefing the top military and political leadership. The test is crucial for validating the country's second-strike capability.</p>\n\n\n\n<p>The Indian Navy had inducted the submarine in August in the Vishakhapatnam-based Ship Building Centre. The sources said that prior to the full-range test of the missile, the DRDO had carried out extensive trials of the launch of the missile to be fired from underwater platforms. The Indian Navy is now planning to carry out more tests of the missile system.</p>\n\n\n\n<p>The Navy has two nuclear submarines with the capability to fire ballistic missiles, including the INS Arihant and the Arighaat. The third boat has also been launched and is expected to be inducted next year.</p>\n","originalUrl":"https://en.tattvanews.com/others/india-successfully-tests-nuclear-capable-3500-km-range-ballistic-missile-%ef%bf%bc/","hasAudio":false,"hasInfographics":false}